rpdk/typescript/__init__.py
rpdk/typescript/codegen.py
rpdk/typescript/package.json
rpdk/typescript/parser.py
rpdk/typescript/utils.py
rpdk/typescript/data/__init__.py
rpdk/typescript/data/create.json
rpdk/typescript/data/handlers.ts
rpdk/typescript/data/integration.npmrc
rpdk/typescript/data/typescript.gitignore
rpdk/typescript/templates/README.md
rpdk/typescript/templates/package.json
rpdk/typescript/templates/tsconfig.json
rpdk/typescript/templates/tsup.config.ts
cfn_cli_typescriptv2_plugin-0.1.0.dist-info/LICENSE
cfn_cli_typescriptv2_plugin-0.1.0.dist-info/METADATA
cfn_cli_typescriptv2_plugin-0.1.0.dist-info/WHEEL
cfn_cli_typescriptv2_plugin-0.1.0.dist-info/entry_points.txt
cfn_cli_typescriptv2_plugin-0.1.0.dist-info/top_level.txt
cfn_cli_typescriptv2_plugin-0.1.0.dist-info/RECORD
