Metadata-Version: 2.1
Name: cfn-cli-typescriptv2-plugin
Version: 0.1.0
Summary: The CloudFormation Resource Provider Development Kit (RPDK) allows you to author your own resource providers that can be used by CloudFormation. This plugin library helps to provide runtime bindings for the execution of your providers by CloudFormation.
Author-email: Richard Simpson <richicoder1@outlook.com>
Project-URL: Homepage, https://github.com/richicoder1/cloudformation-cli-typescriptv2-plugin/
Project-URL: Bug Tracker, https://github.com/richicoder1/cloudformation-cli-typescriptv2-plugin/issues
Classifier: Programming Language :: Python :: 3.9
Classifier: Programming Language :: Python :: 3.10
Classifier: License :: OSI Approved :: Apache Software License
Classifier: Operating System :: OS Independent
Classifier: Development Status :: 5 - Production/Stable
Classifier: Environment :: Console
Classifier: Intended Audience :: Developers
Classifier: Topic :: Software Development :: Build Tools
Classifier: Topic :: Software Development :: Code Generators
Requires-Python: >=3.9
License-File: LICENSE
Requires-Dist: cloudformation-cli (>=0.2.0)
Provides-Extra: dev
Requires-Dist: bandit ; extra == 'dev'
Requires-Dist: black ; extra == 'dev'
Requires-Dist: pytest ; extra == 'dev'
Requires-Dist: pytest-cov ; extra == 'dev'
Requires-Dist: ruff ; extra == 'dev'
